LICENSE
MANIFEST.in
README.md
setup.cfg
setup.py
django_google_cloud_storage/__init__.py
django_google_cloud_storage.egg-info/PKG-INFO
django_google_cloud_storage.egg-info/SOURCES.txt
django_google_cloud_storage.egg-info/dependency_links.txt
django_google_cloud_storage.egg-info/requires.txt
django_google_cloud_storage.egg-info/top_level.txt