Metadata-Version: 1.1
Name: django-google-cloud-storage
Version: 0.0.2
Summary: Google Cloud Storage file backend for Django
Home-page: https://github.com/UseAllFive/django-google-cloud-storage/
Author: Christos Kopanos, Richard Caceres
Author-email: ckopanos@redmob.gr, me@rchrd.net
License: GNU GENERAL PUBLIC LICENSE
Download-URL: https://github.com/UseAllFive/django-google-cloud-storage/tarball/0.0.2
Keywords: django,appengine,google,cloud storage
Platform: UNKNOWN
